{"chunk_definitions":[{"chunk_id":"csetup_chunk","chunk_label":"setup","document_id":"A727B2E4","expansion_state":0,"options":{"engine":"r","include":false,"label":"setup"},"row":78,"row_count":1,"visible":true},{"chunk_id":"cia8twclrj1wz","chunk_label":"unnamed-chunk-1","document_id":"A727B2E4","expansion_state":0,"options":{"engine":"r","label":"unnamed-chunk-32","out.height":"100%","out.width":"100%"},"row":471,"row_count":1,"visible":true}],"default_chunk_options":{},"doc_write_time":1608055983,"working_dir":null}